README.md
setup.cfg
setup.py
hug_explainable/__init__.py
hug_explainable/_version.py
hug_explainable/context_manager.py
hug_explainable/directive.py
hug_explainable/middleware.py
hug_explainable/type.py
hug_explainable.egg-info/PKG-INFO
hug_explainable.egg-info/SOURCES.txt
hug_explainable.egg-info/dependency_links.txt
hug_explainable.egg-info/requires.txt
hug_explainable.egg-info/top_level.txt