Metadata-Version: 1.1
Name: hug-explainable
Version: 0.1.5
Summary: Provides an on demand context manager that makes it easy to profile and explain code blocks / paths within hug.
Home-page: https://github.com/timothycrosley/hug_explainable
Author: Timothy Crosley
Author-email: timothy.crosley@gmail.com
License: MIT
Keywords: Python,Python3
Platform: UNKNOWN
Classifier: Development Status :: 6 - Mature
Classifier: Intended Audience :: Developers
Classifier: Natural Language :: English
Classifier: Environment :: Console
Classifier: License :: OSI Approved :: MIT License
Classifier: Programming Language :: Python
Classifier: Programming Language :: Python :: 3
Classifier: Programming Language :: Python :: 3.2
Classifier: Programming Language :: Python :: 3.3
Classifier: Programming Language :: Python :: 3.4
Classifier: Programming Language :: Python :: 3.5
Classifier: Topic :: Software Development :: Libraries
Classifier: Topic :: Utilities
